nlzss11.cp312-win_amd64.pyd
nlzss11-1.8.dist-info/LICENSE.md
nlzss11-1.8.dist-info/METADATA
nlzss11-1.8.dist-info/WHEEL
nlzss11-1.8.dist-info/top_level.txt
nlzss11-1.8.dist-info/RECORD
