Metadata-Version: 2.1
Name: nlzss11
Version: 1.8
Summary: Library for data (de)compression using Nintendo's lzss11 algorithm
Home-page: https://github.com/lepelog/nlzss11
Author: lepelog
Classifier: License :: OSI Approved :: GNU General Public License v2 or later (GPLv2+)
Classifier: Topic :: Software Development :: Libraries
Classifier: Operating System :: OS Independent
Classifier: Programming Language :: C++
Classifier: Programming Language :: Python :: 3 :: Only
Requires-Python: >=3.6
License-File: LICENSE.md
